src/__init__.py
src/cli.py
src/commands/__init__.py
src/commands/merge_xmp.py
src/commands/refresh_album_metadata.py
src/commands/run_job.py
src/commands/version.py
src/utils/__init__.py
src/utils/utils.py
immich_tools-1.9.1.dist-info/METADATA
immich_tools-1.9.1.dist-info/WHEEL
immich_tools-1.9.1.dist-info/entry_points.txt
immich_tools-1.9.1.dist-info/top_level.txt
immich_tools-1.9.1.dist-info/RECORD
