Metadata-Version: 2.4
Name: immich-tools
Version: 1.9.1
Requires-Dist: click
Requires-Dist: requests
Requires-Dist: PyExifTool
Dynamic: requires-dist
